Workbook

Sheet Risultati
A1: Reddito | D1: Fatturato lordo | F1: Reddito netto | H1: Totale da pagare
A2: Totale fatturato lordo | B2: =Calcoli!B1 -> 0 | D2: =B2 -> 0 | F2: =B3 -> 0 | H2: =SUM(B7:B11) -> 0
A3: Totale reddito netto | B3: =MAX(0,B2-H2) -> 0
A6: Da pagare
A7: IRPEF da pagare | B7: =Calcoli!B8 -> 0
A8: INPS da pagare | B8: =IF(Impostazioni!B3="Camera di Commercio",IF(Impostazioni!B6,0,IF(Impostazioni!B5,Calcoli!B17,Calcoli!B16)),IF(Impostazioni!B3="Gestione separata",Calcoli!B22,Calcoli!B27)) -> 0
A9: Commercialista da pagare | B9: =Impostazioni!B7 -> 0
A10: Marche da bollo | B10: =Calcoli!B5 -> 0
A11: Altro da pagare | B11: =Impostazioni!B8 -> 0

Sheet Pagamenti
A1: N | B1: Data | C1: Cliente | D1: Imponibile | E1: Codice ATECO

Sheet Investimenti
A1: Investiti | E1: Disinvestiti / Pagati | J1: Totale da pagare | L1: Saldo da investire
A2: Data | B2: Valore | C2: Note | E2: Data | F2: Valore | G2: Note | J2: =Risultati!H2 -> 0 | L2: =J2-SUM(F2:F1000)-SUM(B3:B1000) -> 0

Sheet Impostazioni
A1: Codice ATECO | C1: (Se hai piú codici ATECO non inserire niente e mettili sulle fatture)
A2: Aliquota imposta sostitutiva IRPEF | B2: 0.15 | C2: (5% nei primi 5 anni da forfettario, 15% poi)
A3: Tipo INPS | B3: Gestione separata | C3: (Tipo di gestione INPS)
A4: Commerciante/artigiano | B4: Commerciante | C4: (Compila se INPS é Camera di Commercio, altrimenti non viene preso in considerazione)
A5: Sconto INPS commercianti/artigiani | B5: FALSE | C5: (É possibile avere una riduzione per artigiani e commercianti)
A6: Lavoro dipendente | B6: FALSE | C6: (Se sei dipendente e sei iscritto alla Camera di Commercio per l'INPS non lo paghi, con la Gestione separata é ridotto)
A7: Costo annuale commercialista (compresa IVA) | B7: 0
A8: Altri costi annuali (software gestione fatture, ecc.) | B8: 0

Sheet Valori fissi 2025
A1: Limite permanenza forfettario | B1: 85000
A2: Limite ultimo permanenza forfettario | B2: 100000
A4: INPS CCIAA
A5: Contributi fissi commercianti | B5: 4549.7
A6: Contributi fissi artigiani | B6: 4460.64
A7: Sconto | B7: 0.35
A9: Primo limite fisso contributi | B9: 18555
A10: Percentuale contributi variabili commercianti primo limite | B10: 0.2448
A11: Percentuale contributi variabili artigiani primo limite | B11: 0.24
A13: Secondo limite fisso contributi | B13: 55448
A14: Percentuale contributi variabili commercianti secondo limite | B14: 0.2548
A15: Percentuale contributi variabili artigiani secondo limite | B15: 0.25
A17: INPS Gestione separata
A18: Percentuale contributi variabili in gestione separata | B18: 0.2623
A19: Percentuale contributi variabili in gestione separata da dipendente | B19: 0.24
A21: INPS Liberi professionisti
A22: Percentuale contributi cassa professionale | B22: 0
A24: Costo fatture
A25: Limite marca da bollo | B25: 77.47
A26: Costo marca da bollo | B26: 2

Sheet Calcoli
A1: Income lordo | B1: =IF(Impostazioni!B1<>"",SUM(Pagamenti!D2:D1006),SUM('Somma Fatture ATECO'!B2:B1006)) -> 0
A2: Reddito lordo | B2: =IF(Impostazioni!B1<>"",B1*IFERROR(VLOOKUP(Impostazioni!B1,'Codici ATECO 2022'!A$2:C1006,3),0),SUM('Somma Fatture ATECO'!D2:D1006)) -> 0
A4: Fatture con marca da bollo | B4: =COUNTIF(Pagamenti!D3:D1006,">"&'Valori fissi 2025'!B25) -> 0
A5: Costo marche da bollo | B5: =B4*'Valori fissi 2025'!B26 -> 0
A7: IRPEF
A8: IRPEF da pagare | B8: =MAX(0,(B2-IF(Impostazioni!B3="Camera di Commercio",IF(Impostazioni!B5,B17,B16),IF(Impostazioni!B3="Gestione separata",B22,B27)))*Impostazioni!B2) -> 0
A11: INPS Gestione commercianti
A12: Contributi fissi | B12: =IF(Impostazioni!B4="Commerciante",'Valori fissi 2025'!B5,'Valori fissi 2025'!B6) -> 4549.7
A13: Reddito eccedente primo limite INPS | B13: =IF(B2-'Valori fissi 2025'!B9 > 0,MIN(B2-'Valori fissi 2025'!B9,'Valori fissi 2025'!B13-'Valori fissi 2025'!B9),0) -> 0
A14: Reddito eccedente secondo limite INPS | B14: =IF(B2-'Valori fissi 2025'!B13 > 0,B2-'Valori fissi 2025'!B13,0) -> 0
A15: Contributi da pagare in eccedenza | B15: =(B13*IF(Impostazioni!B4="Commerciante",'Valori fissi 2025'!B10,'Valori fissi 2025'!B11))+(B14*IF(Impostazioni!B4="Commerciante",'Valori fissi 2025'!B14,'Valori fissi 2025'!B15)) -> 0
A16: Totale contributi da pagare | B16: =B12+B15 -> 4549.7
A17: Totale contributi da pagare con sconto | B17: =B16*(1-'Valori fissi 2025'!B7) -> 2957.305
A20: INPS Gestione separata
A21: Percentuale contributi da pagare | B21: =IF(Impostazioni!B6,'Valori fissi 2025'!B19,'Valori fissi 2025'!B18) -> 0.2623
A22: Contributi da pagare | B22: =B2*B21 -> 0
A25: INPS Libero professionista
A26: Aliquota contributi | B26: ='Valori fissi 2025'!B22 -> 0
A27: Contributi da pagare | B27: =B2*B26 -> 0

Sheet Somma Fatture ATECO
A1: Codici ATECO | B1: Somma | C1: Coefficiente di redditivitá | D1: Reddito netto
A2: {=_xludf.UNIQUE(Pagamenti!E2:E1240)} -> #NAME? | B2: =SUMIF(Pagamenti!E$2:E1240,A2,Pagamenti!D$2:D1240) -> 0 | C2: =IFERROR(VLOOKUP(A2,'Codici ATECO 2022'!A$2:C1240,3),0) -> 0 | D2: =B2*C2 -> 0
B3: =SUMIF(Pagamenti!E$2:E1240,A3,Pagamenti!D$2:D1240) -> 0 | C3: =IFERROR(VLOOKUP(A3,'Codici ATECO 2022'!A$2:C1240,3),0) -> 0 | D3: =B3*C3 -> 0
B4: =SUMIF(Pagamenti!E$2:E1240,A4,Pagamenti!D$2:D1240) -> 0 | C4: =IFERROR(VLOOKUP(A4,'Codici ATECO 2022'!A$2:C1240,3),0) -> 0 | D4: =B4*C4 -> 0
B5: =SUMIF(Pagamenti!E$2:E1240,A5,Pagamenti!D$2:D1240) -> 0 | C5: =IFERROR(VLOOKUP(A5,'Codici ATECO 2022'!A$2:C1240,3),0) -> 0 | D5: =B5*C5 -> 0
B6: =SUMIF(Pagamenti!E$2:E1240,A6,Pagamenti!D$2:D1240) -> 0 | C6: =IFERROR(VLOOKUP(A6,'Codici ATECO 2022'!A$2:C1240,3),0) -> 0 | D6: =B6*C6 -> 0
B7: =SUMIF(Pagamenti!E$2:E1240,A7,Pagamenti!D$2:D1240) -> 0 | C7: =IFERROR(VLOOKUP(A7,'Codici ATECO 2022'!A$2:C1240,3),0) -> 0 | D7: =B7*C7 -> 0
B8: =SUMIF(Pagamenti!E$2:E1240,A8,Pagamenti!D$2:D1240) -> 0 | C8: =IFERROR(VLOOKUP(A8,'Codici ATECO 2022'!A$2:C1240,3),0) -> 0 | D8: =B8*C8 -> 0
B9: =SUMIF(Pagamenti!E$2:E1240,A9,Pagamenti!D$2:D1240) -> 0 | C9: =IFERROR(VLOOKUP(A9,'Codici ATECO 2022'!A$2:C1240,3),0) -> 0 | D9: =B9*C9 -> 0
B10: =SUMIF(Pagamenti!E$2:E1240,A10,Pagamenti!D$2:D1240) -> 0 | C10: =IFERROR(VLOOKUP(A10,'Codici ATECO 2022'!A$2:C1240,3),0) -> 0 | D10: =B10*C10 -> 0
B11: =SUMIF(Pagamenti!E$2:E1240,A11,Pagamenti!D$2:D1240) -> 0 | C11: =IFERROR(VLOOKUP(A11,'Codici ATECO 2022'!A$2:C1240,3),0) -> 0 | D11: =B11*C11 -> 0
B12: =SUMIF(Pagamenti!E$2:E1240,A12,Pagamenti!D$2:D1240) -> 0 | C12: =IFERROR(VLOOKUP(A12,'Codici ATECO 2022'!A$2:C1240,3),0) -> 0 | D12: =B12*C12 -> 0
B13: =SUMIF(Pagamenti!E$2:E1240,A13,Pagamenti!D$2:D1240) -> 0 | C13: =IFERROR(VLOOKUP(A13,'Codici ATECO 2022'!A$2:C1240,3),0) -> 0 | D13: =B13*C13 -> 0
B14: =SUMIF(Pagamenti!E$2:E1240,A14,Pagamenti!D$2:D1240) -> 0 | C14: =IFERROR(VLOOKUP(A14,'Codici ATECO 2022'!A$2:C1240,3),0) -> 0 | D14: =B14*C14 -> 0
B15: =SUMIF(Pagamenti!E$2:E1240,A15,Pagamenti!D$2:D1240) -> 0 | C15: =IFERROR(VLOOKUP(A15,'Codici ATECO 2022'!A$2:C1240,3),0) -> 0 | D15: =B15*C15 -> 0
B16: =SUMIF(Pagamenti!E$2:E1240,A16,Pagamenti!D$2:D1240) -> 0 | C16: =IFERROR(VLOOKUP(A16,'Codici ATECO 2022'!A$2:C1240,3),0) -> 0 | D16: =B16*C16 -> 0
B17: =SUMIF(Pagamenti!E$2:E1240,A17,Pagamenti!D$2:D1240) -> 0 | C17: =IFERROR(VLOOKUP(A17,'Codici ATECO 2022'!A$2:C1240,3),0) -> 0 | D17: =B17*C17 -> 0
B18: =SUMIF(Pagamenti!E$2:E1240,A18,Pagamenti!D$2:D1240) -> 0 | C18: =IFERROR(VLOOKUP(A18,'Codici ATECO 2022'!A$2:C1240,3),0) -> 0 | D18: =B18*C18 -> 0
B19: =SUMIF(Pagamenti!E$2:E1240,A19,Pagamenti!D$2:D1240) -> 0 | C19: =IFERROR(VLOOKUP(A19,'Codici ATECO 2022'!A$2:C1240,3),0) -> 0 | D19: =B19*C19 -> 0
B20: =SUMIF(Pagamenti!E$2:E1240,A20,Pagamenti!D$2:D1240) -> 0 | C20: =IFERROR(VLOOKUP(A20,'Codici ATECO 2022'!A$2:C1240,3),0) -> 0 | D20: =B20*C20 -> 0
B21: =SUMIF(Pagamenti!E$2:E1240,A21,Pagamenti!D$2:D1240) -> 0 | C21: =IFERROR(VLOOKUP(A21,'Codici ATECO 2022'!A$2:C1240,3),0) -> 0 | D21: =B21*C21 -> 0
B22: =SUMIF(Pagamenti!E$2:E1240,A22,Pagamenti!D$2:D1240) -> 0 | C22: =IFERROR(VLOOKUP(A22,'Codici ATECO 2022'!A$2:C1240,3),0) -> 0 | D22: =B22*C22 -> 0
B23: =SUMIF(Pagamenti!E$2:E1240,A23,Pagamenti!D$2:D1240) -> 0 | C23: =IFERROR(VLOOKUP(A23,'Codici ATECO 2022'!A$2:C1240,3),0) -> 0 | D23: =B23*C23 -> 0
B24: =SUMIF(Pagamenti!E$2:E1240,A24,Pagamenti!D$2:D1240) -> 0 | C24: =IFERROR(VLOOKUP(A24,'Codici ATECO 2022'!A$2:C1240,3),0) -> 0 | D24: =B24*C24 -> 0
B25: =SUMIF(Pagamenti!E$2:E1240,A25,Pagamenti!D$2:D1240) -> 0 | C25: =IFERROR(VLOOKUP(A25,'Codici ATECO 2022'!A$2:C1240,3),0) -> 0 | D25: =B25*C25 -> 0
B26: =SUMIF(Pagamenti!E$2:E1240,A26,Pagamenti!D$2:D1240) -> 0 | C26: =IFERROR(VLOOKUP(A26,'Codici ATECO 2022'!A$2:C1240,3),0) -> 0 | D26: =B26*C26 -> 0
B27: =SUMIF(Pagamenti!E$2:E1240,A27,Pagamenti!D$2:D1240) -> 0 | C27: =IFERROR(VLOOKUP(A27,'Codici ATECO 2022'!A$2:C1240,3),0) -> 0 | D27: =B27*C27 -> 0
B28: =SUMIF(Pagamenti!E$2:E1240,A28,Pagamenti!D$2:D1240) -> 0 | C28: =IFERROR(VLOOKUP(A28,'Codici ATECO 2022'!A$2:C1240,3),0) -> 0 | D28: =B28*C28 -> 0
B29: =SUMIF(Pagamenti!E$2:E1240,A29,Pagamenti!D$2:D1240) -> 0 | C29: =IFERROR(VLOOKUP(A29,'Codici ATECO 2022'!A$2:C1240,3),0) -> 0 | D29: =B29*C29 -> 0
B30: =SUMIF(Pagamenti!E$2:E1240,A30,Pagamenti!D$2:D1240) -> 0 | C30: =IFERROR(VLOOKUP(A30,'Codici ATECO 2022'!A$2:C1240,3),0) -> 0 | D30: =B30*C30 -> 0
B31: =SUMIF(Pagamenti!E$2:E1240,A31,Pagamenti!D$2:D1240) -> 0 | C31: =IFERROR(VLOOKUP(A31,'Codici ATECO 2022'!A$2:C1240,3),0) -> 0 | D31: =B31*C31 -> 0
B32: =SUMIF(Pagamenti!E$2:E1240,A32,Pagamenti!D$2:D1240) -> 0 | C32: =IFERROR(VLOOKUP(A32,'Codici ATECO 2022'!A$2:C1240,3),0) -> 0 | D32: =B32*C32 -> 0
B33: =SUMIF(Pagamenti!E$2:E1240,A33,Pagamenti!D$2:D1240) -> 0 | C33: =IFERROR(VLOOKUP(A33,'Codici ATECO 2022'!A$2:C1240,3),0) -> 0 | D33: =B33*C33 -> 0
B34: =SUMIF(Pagamenti!E$2:E1240,A34,Pagamenti!D$2:D1240) -> 0 | C34: =IFERROR(VLOOKUP(A34,'Codici ATECO 2022'!A$2:C1240,3),0) -> 0 | D34: =B34*C34 -> 0
B35: =SUMIF(Pagamenti!E$2:E1240,A35,Pagamenti!D$2:D1240) -> 0 | C35: =IFERROR(VLOOKUP(A35,'Codici ATECO 2022'!A$2:C1240,3),0) -> 0 | D35: =B35*C35 -> 0
B36: =SUMIF(Pagamenti!E$2:E1240,A36,Pagamenti!D$2:D1240) -> 0 | C36: =IFERROR(VLOOKUP(A36,'Codici ATECO 2022'!A$2:C1240,3),0) -> 0 | D36: =B36*C36 -> 0
B37: =SUMIF(Pagamenti!E$2:E1240,A37,Pagamenti!D$2:D1240) -> 0 | C37: =IFERROR(VLOOKUP(A37,'Codici ATECO 2022'!A$2:C1240,3),0) -> 0 | D37: =B37*C37 -> 0
B38: =SUMIF(Pagamenti!E$2:E1240,A38,Pagamenti!D$2:D1240) -> 0 | C38: =IFERROR(VLOOKUP(A38,'Codici ATECO 2022'!A$2:C1240,3),0) -> 0 | D38: =B38*C38 -> 0
B39: =SUMIF(Pagamenti!E$2:E1240,A39,Pagamenti!D$2:D1240) -> 0 | C39: =IFERROR(VLOOKUP(A39,'Codici ATECO 2022'!A$2:C1240,3),0) -> 0 | D39: =B39*C39 -> 0
B40: =SUMIF(Pagamenti!E$2:E1240,A40,Pagamenti!D$2:D1240) -> 0 | C40: =IFERROR(VLOOKUP(A40,'Codici ATECO 2022'!A$2:C1240,3),0) -> 0 | D40: =B40*C40 -> 0
B41: =SUMIF(Pagamenti!E$2:E1240,A41,Pagamenti!D$2:D1240) -> 0 | C41: =IFERROR(VLOOKUP(A41,'Codici ATECO 2022'!A$2:C1240,3),0) -> 0 | D41: =B41*C41 -> 0
B42: =SUMIF(Pagamenti!E$2:E1240,A42,Pagamenti!D$2:D1240) -> 0 | C42: =IFERROR(VLOOKUP(A42,'Codici ATECO 2022'!A$2:C1240,3),0) -> 0 | D42: =B42*C42 -> 0
B43: =SUMIF(Pagamenti!E$2:E1240,A43,Pagamenti!D$2:D1240) -> 0 | C43: =IFERROR(VLOOKUP(A43,'Codici ATECO 2022'!A$2:C1240,3),0) -> 0 | D43: =B43*C43 -> 0
B44: =SUMIF(Pagamenti!E$2:E1240,A44,Pagamenti!D$2:D1240) -> 0 | C44: =IFERROR(VLOOKUP(A44,'Codici ATECO 2022'!A$2:C1240,3),0) -> 0 | D44: =B44*C44 -> 0
B45: =SUMIF(Pagamenti!E$2:E1240,A45,Pagamenti!D$2:D1240) -> 0 | C45: =IFERROR(VLOOKUP(A45,'Codici ATECO 2022'!A$2:C1240,3),0) -> 0 | D45: =B45*C45 -> 0
B46: =SUMIF(Pagamenti!E$2:E1240,A46,Pagamenti!D$2:D1240) -> 0 | C46: =IFERROR(VLOOKUP(A46,'Codici ATECO 2022'!A$2:C1240,3),0) -> 0 | D46: =B46*C46 -> 0
B47: =SUMIF(Pagamenti!E$2:E1240,A47,Pagamenti!D$2:D1240) -> 0 | C47: =IFERROR(VLOOKUP(A47,'Codici ATECO 2022'!A$2:C1240,3),0) -> 0 | D47: =B47*C47 -> 0
B48: =SUMIF(Pagamenti!E$2:E1240,A48,Pagamenti!D$2:D1240) -> 0 | C48: =IFERROR(VLOOKUP(A48,'Codici ATECO 2022'!A$2:C1240,3),0) -> 0 | D48: =B48*C48 -> 0
B49: =SUMIF(Pagamenti!E$2:E1240,A49,Pagamenti!D$2:D1240) -> 0 | C49: =IFERROR(VLOOKUP(A49,'Codici ATECO 2022'!A$2:C1240,3),0) -> 0 | D49: =B49*C49 -> 0
B50: =SUMIF(Pagamenti!E$2:E1240,A50,Pagamenti!D$2:D1240) -> 0 | C50: =IFERROR(VLOOKUP(A50,'Codici ATECO 2022'!A$2:C1240,3),0) -> 0 | D50: =B50*C50 -> 0
B51: =SUMIF(Pagamenti!E$2:E1240,A51,Pagamenti!D$2:D1240) -> 0 | C51: =IFERROR(VLOOKUP(A51,'Codici ATECO 2022'!A$2:C1240,3),0) -> 0 | D51: =B51*C51 -> 0
B52: =SUMIF(Pagamenti!E$2:E1240,A52,Pagamenti!D$2:D1240) -> 0 | C52: =IFERROR(VLOOKUP(A52,'Codici ATECO 2022'!A$2:C1240,3),0) -> 0 | D52: =B52*C52 -> 0
B53: =SUMIF(Pagamenti!E$2:E1240,A53,Pagamenti!D$2:D1240) -> 0 | C53: =IFERROR(VLOOKUP(A53,'Codici ATECO 2022'!A$2:C1240,3),0) -> 0 | D53: =B53*C53 -> 0
B54: =SUMIF(Pagamenti!E$2:E1240,A54,Pagamenti!D$2:D1240) -> 0 | C54: =IFERROR(VLOOKUP(A54,'Codici ATECO 2022'!A$2:C1240,3),0) -> 0 | D54: =B54*C54 -> 0
B55: =SUMIF(Pagamenti!E$2:E1240,A55,Pagamenti!D$2:D1240) -> 0 | C55: =IFERROR(VLOOKUP(A55,'Codici ATECO 2022'!A$2:C1240,3),0) -> 0 | D55: =B55*C55 -> 0
B56: =SUMIF(Pagamenti!E$2:E1240,A56,Pagamenti!D$2:D1240) -> 0 | C56: =IFERROR(VLOOKUP(A56,'Codici ATECO 2022'!A$2:C1240,3),0) -> 0 | D56: =B56*C56 -> 0
B57: =SUMIF(Pagamenti!E$2:E1240,A57,Pagamenti!D$2:D1240) -> 0 | C57: =IFERROR(VLOOKUP(A57,'Codici ATECO 2022'!A$2:C1240,3),0) -> 0 | D57: =B57*C57 -> 0
B58: =SUMIF(Pagamenti!E$2:E1240,A58,Pagamenti!D$2:D1240) -> 0 | C58: =IFERROR(VLOOKUP(A58,'Codici ATECO 2022'!A$2:C1240,3),0) -> 0 | D58: =B58*C58 -> 0
B59: =SUMIF(Pagamenti!E$2:E1240,A59,Pagamenti!D$2:D1240) -> 0 | C59: =IFERROR(VLOOKUP(A59,'Codici ATECO 2022'!A$2:C1240,3),0) -> 0 | D59: =B59*C59 -> 0
B60: =SUMIF(Pagamenti!E$2:E1240,A60,Pagamenti!D$2:D1240) -> 0 | C60: =IFERROR(VLOOKUP(A60,'Codici ATECO 2022'!A$2:C1240,3),0) -> 0 | D60: =B60*C60 -> 0
B61: =SUMIF(Pagamenti!E$2:E1240,A61,Pagamenti!D$2:D1240) -> 0 | C61: =IFERROR(VLOOKUP(A61,'Codici ATECO 2022'!A$2:C1240,3),0) -> 0 | D61: =B61*C61 -> 0
B62: =SUMIF(Pagamenti!E$2:E1240,A62,Pagamenti!D$2:D1240) -> 0 | C62: =IFERROR(VLOOKUP(A62,'Codici ATECO 2022'!A$2:C1240,3),0) -> 0 | D62: =B62*C62 -> 0
B63: =SUMIF(Pagamenti!E$2:E1240,A63,Pagamenti!D$2:D1240) -> 0 | C63: =IFERROR(VLOOKUP(A63,'Codici ATECO 2022'!A$2:C1240,3),0) -> 0 | D63: =B63*C63 -> 0
B64: =SUMIF(Pagamenti!E$2:E1240,A64,Pagamenti!D$2:D1240) -> 0 | C64: =IFERROR(VLOOKUP(A64,'Codici ATECO 2022'!A$2:C1240,3),0) -> 0 | D64: =B64*C64 -> 0
B65: =SUMIF(Pagamenti!E$2:E1240,A65,Pagamenti!D$2:D1240) -> 0 | C65: =IFERROR(VLOOKUP(A65,'Codici ATECO 2022'!A$2:C1240,3),0) -> 0 | D65: =B65*C65 -> 0
B66: =SUMIF(Pagamenti!E$2:E1240,A66,Pagamenti!D$2:D1240) -> 0 | C66: =IFERROR(VLOOKUP(A66,'Codici ATECO 2022'!A$2:C1240,3),0) -> 0 | D66: =B66*C66 -> 0
B67: =SUMIF(Pagamenti!E$2:E1240,A67,Pagamenti!D$2:D1240) -> 0 | C67: =IFERROR(VLOOKUP(A67,'Codici ATECO 2022'!A$2:C1240,3),0) -> 0 | D67: =B67*C67 -> 0
B68: =SUMIF(Pagamenti!E$2:E1240,A68,Pagamenti!D$2:D1240) -> 0 | C68: =IFERROR(VLOOKUP(A68,'Codici ATECO 2022'!A$2:C1240,3),0) -> 0 | D68: =B68*C68 -> 0
B69: =SUMIF(Pagamenti!E$2:E1240,A69,Pagamenti!D$2:D1240) -> 0 | C69: =IFERROR(VLOOKUP(A69,'Codici ATECO 2022'!A$2:C1240,3),0) -> 0 | D69: =B69*C69 -> 0
B70: =SUMIF(Pagamenti!E$2:E1240,A70,Pagamenti!D$2:D1240) -> 0 | C70: =IFERROR(VLOOKUP(A70,'Codici ATECO 2022'!A$2:C1240,3),0) -> 0 | D70: =B70*C70 -> 0
B71: =SUMIF(Pagamenti!E$2:E1240,A71,Pagamenti!D$2:D1240) -> 0 | C71: =IFERROR(VLOOKUP(A71,'Codici ATECO 2022'!A$2:C1240,3),0) -> 0 | D71: =B71*C71 -> 0
B72: =SUMIF(Pagamenti!E$2:E1240,A72,Pagamenti!D$2:D1240) -> 0 | C72: =IFERROR(VLOOKUP(A72,'Codici ATECO 2022'!A$2:C1240,3),0) -> 0 | D72: =B72*C72 -> 0
B73: =SUMIF(Pagamenti!E$2:E1240,A73,Pagamenti!D$2:D1240) -> 0 | C73: =IFERROR(VLOOKUP(A73,'Codici ATECO 2022'!A$2:C1240,3),0) -> 0 | D73: =B73*C73 -> 0
B74: =SUMIF(Pagamenti!E$2:E1240,A74,Pagamenti!D$2:D1240) -> 0 | C74: =IFERROR(VLOOKUP(A74,'Codici ATECO 2022'!A$2:C1240,3),0) -> 0 | D74: =B74*C74 -> 0
B75: =SUMIF(Pagamenti!E$2:E1240,A75,Pagamenti!D$2:D1240) -> 0 | C75: =IFERROR(VLOOKUP(A75,'Codici ATECO 2022'!A$2:C1240,3),0) -> 0 | D75: =B75*C75 -> 0
B76: =SUMIF(Pagamenti!E$2:E1240,A76,Pagamenti!D$2:D1240) -> 0 | C76: =IFERROR(VLOOKUP(A76,'Codici ATECO 2022'!A$2:C1240,3),0) -> 0 | D76: =B76*C76 -> 0
B77: =SUMIF(Pagamenti!E$2:E1240,A77,Pagamenti!D$2:D1240) -> 0 | C77: =IFERROR(VLOOKUP(A77,'Codici ATECO 2022'!A$2:C1240,3),0) -> 0 | D77: =B77*C77 -> 0
B78: =SUMIF(Pagamenti!E$2:E1240,A78,Pagamenti!D$2:D1240) -> 0 | C78: =IFERROR(VLOOKUP(A78,'Codici ATECO 2022'!A$2:C1240,3),0) -> 0 | D78: =B78*C78 -> 0
B79: =SUMIF(Pagamenti!E$2:E1240,A79,Pagamenti!D$2:D1240) -> 0 | C79: =IFERROR(VLOOKUP(A79,'Codici ATECO 2022'!A$2:C1240,3),0) -> 0 | D79: =B79*C79 -> 0
B80: =SUMIF(Pagamenti!E$2:E1240,A80,Pagamenti!D$2:D1240) -> 0 | C80: =IFERROR(VLOOKUP(A80,'Codici ATECO 2022'!A$2:C1240,3),0) -> 0 | D80: =B80*C80 -> 0
B81: =SUMIF(Pagamenti!E$2:E1240,A81,Pagamenti!D$2:D1240) -> 0 | C81: =IFERROR(VLOOKUP(A81,'Codici ATECO 2022'!A$2:C1240,3),0) -> 0 | D81: =B81*C81 -> 0
B82: =SUMIF(Pagamenti!E$2:E1240,A82,Pagamenti!D$2:D1240) -> 0 | C82: =IFERROR(VLOOKUP(A82,'Codici ATECO 2022'!A$2:C1240,3),0) -> 0 | D82: =B82*C82 -> 0
B83: =SUMIF(Pagamenti!E$2:E1240,A83,Pagamenti!D$2:D1240) -> 0 | C83: =IFERROR(VLOOKUP(A83,'Codici ATECO 2022'!A$2:C1240,3),0) -> 0 | D83: =B83*C83 -> 0
B84: =SUMIF(Pagamenti!E$2:E1240,A84,Pagamenti!D$2:D1240) -> 0 | C84: =IFERROR(VLOOKUP(A84,'Codici ATECO 2022'!A$2:C1240,3),0) -> 0 | D84: =B84*C84 -> 0
B85: =SUMIF(Pagamenti!E$2:E1240,A85,Pagamenti!D$2:D1240) -> 0 | C85: =IFERROR(VLOOKUP(A85,'Codici ATECO 2022'!A$2:C1240,3),0) -> 0 | D85: =B85*C85 -> 0
B86: =SUMIF(Pagamenti!E$2:E1240,A86,Pagamenti!D$2:D1240) -> 0 | C86: =IFERROR(VLOOKUP(A86,'Codici ATECO 2022'!A$2:C1240,3),0) -> 0 | D86: =B86*C86 -> 0
B87: =SUMIF(Pagamenti!E$2:E1240,A87,Pagamenti!D$2:D1240) -> 0 | C87: =IFERROR(VLOOKUP(A87,'Codici ATECO 2022'!A$2:C1240,3),0) -> 0 | D87: =B87*C87 -> 0
B88: =SUMIF(Pagamenti!E$2:E1240,A88,Pagamenti!D$2:D1240) -> 0 | C88: =IFERROR(VLOOKUP(A88,'Codici ATECO 2022'!A$2:C1240,3),0) -> 0 | D88: =B88*C88 -> 0
B89: =SUMIF(Pagamenti!E$2:E1240,A89,Pagamenti!D$2:D1240) -> 0 | C89: =IFERROR(VLOOKUP(A89,'Codici ATECO 2022'!A$2:C1240,3),0) -> 0 | D89: =B89*C89 -> 0
B90: =SUMIF(Pagamenti!E$2:E1240,A90,Pagamenti!D$2:D1240) -> 0 | C90: =IFERROR(VLOOKUP(A90,'Codici ATECO 2022'!A$2:C1240,3),0) -> 0 | D90: =B90*C90 -> 0
B91: =SUMIF(Pagamenti!E$2:E1240,A91,Pagamenti!D$2:D1240) -> 0 | C91: =IFERROR(VLOOKUP(A91,'Codici ATECO 2022'!A$2:C1240,3),0) -> 0 | D91: =B91*C91 -> 0
B92: =SUMIF(Pagamenti!E$2:E1240,A92,Pagamenti!D$2:D1240) -> 0 | C92: =IFERROR(VLOOKUP(A92,'Codici ATECO 2022'!A$2:C1240,3),0) -> 0 | D92: =B92*C92 -> 0
B93: =SUMIF(Pagamenti!E$2:E1240,A93,Pagamenti!D$2:D1240) -> 0 | C93: =IFERROR(VLOOKUP(A93,'Codici ATECO 2022'!A$2:C1240,3),0) -> 0 | D93: =B93*C93 -> 0
B94: =SUMIF(Pagamenti!E$2:E1240,A94,Pagamenti!D$2:D1240) -> 0 | C94: =IFERROR(VLOOKUP(A94,'Codici ATECO 2022'!A$2:C1240,3),0) -> 0 | D94: =B94*C94 -> 0
B95: =SUMIF(Pagamenti!E$2:E1240,A95,Pagamenti!D$2:D1240) -> 0 | C95: =IFERROR(VLOOKUP(A95,'Codici ATECO 2022'!A$2:C1240,3),0) -> 0 | D95: =B95*C95 -> 0
B96: =SUMIF(Pagamenti!E$2:E1240,A96,Pagamenti!D$2:D1240) -> 0 | C96: =IFERROR(VLOOKUP(A96,'Codici ATECO 2022'!A$2:C1240,3),0) -> 0 | D96: =B96*C96 -> 0
B97: =SUMIF(Pagamenti!E$2:E1240,A97,Pagamenti!D$2:D1240) -> 0 | C97: =IFERROR(VLOOKUP(A97,'Codici ATECO 2022'!A$2:C1240,3),0) -> 0 | D97: =B97*C97 -> 0
B98: =SUMIF(Pagamenti!E$2:E1240,A98,Pagamenti!D$2:D1240) -> 0 | C98: =IFERROR(VLOOKUP(A98,'Codici ATECO 2022'!A$2:C1240,3),0) -> 0 | D98: =B98*C98 -> 0
B99: =SUMIF(Pagamenti!E$2:E1240,A99,Pagamenti!D$2:D1240) -> 0 | C99: =IFERROR(VLOOKUP(A99,'Codici ATECO 2022'!A$2:C1240,3),0) -> 0 | D99: =B99*C99 -> 0
B100: =SUMIF(Pagamenti!E$2:E1240,A100,Pagamenti!D$2:D1240) -> 0 | C100: =IFERROR(VLOOKUP(A100,'Codici ATECO 2022'!A$2:C1240,3),0) -> 0 | D100: =B100*C100 -> 0
...

Sheet Codici ATECO 2022
A1: Codice ATECO | B1: Titolo ATECO | C1: Coefficiente di redditivitá
A2: 01.11.10 | B2: Coltivazione di cereali (escluso il riso) | C2: 0.67
A3: 01.11.20 | B3: Coltivazione di semi oleosi | C3: 0.67
A4: 01.11.30 | B4: Coltivazione di legumi da granella | C4: 0.67
A5: 01.11.40 | B5: Coltivazioni miste di cereali, legumi da granella e semi oleosi | C5: 0.67
A6: 01.12.00 | B6: Coltivazione di riso | C6: 0.67
A7: 01.13.10 | B7: Coltivazione di ortaggi (inclusi i meloni) in foglia, a fusto, a frutto, in radici, bulbi e tuberi in piena aria (escluse barbabietola da zucchero e patate) | C7: 0.67
A8: 01.13.21 | B8: Coltivazione di ortaggi (inclusi i meloni) in foglia, a fusto, a frutto, in radici, bulbi e tuberi in colture protette fuori suolo (escluse barbabietola da zucchero e patate) | C8: 0.67
A9: 01.13.29 | B9: Coltivazione di ortaggi (inclusi i meloni) in foglia, a fusto, a frutto, in radici, bulbi e tuberi in colture protette ad esclusione delle colture fuori suolo (escluse barbabietola da zucchero e patate) | C9: 0.67
A10: 01.13.30 | B10: Coltivazione di barbabietola da zucchero | C10: 0.67
A11: 01.13.40 | B11: Coltivazione di patate | C11: 0.67
A12: 01.14.00 | B12: Coltivazione di canna da zucchero | C12: 0.67
A13: 01.15.00 | B13: Coltivazione di tabacco | C13: 0.67
... A1240: 99.00.00 | B1240: Organizzazioni ed organismi extraterritoriali | C1240: 0.67
